klustakwik2-0.2.7.dist-info/top_level.txt
klustakwik2-0.2.7.dist-info/WHEEL
klustakwik2-0.2.7.dist-info/entry_points.txt
klustakwik2-0.2.7.dist-info/METADATA
klustakwik2-0.2.7.dist-info/RECORD
klustakwik2/input_output.py
klustakwik2/precomputations.py
klustakwik2/logger.py
klustakwik2/linear_algebra.py
klustakwik2/monitoring.py
klustakwik2/mask_starts.py
klustakwik2/default_parameters.py
klustakwik2/data.py
klustakwik2/debugtools.py
klustakwik2/clustering.py
klustakwik2/__init__.py
klustakwik2/.libs/libgomp-3300acd3.so.1.0.0
klustakwik2/scripts/kk2_legacy.py
klustakwik2/scripts/tools.py
klustakwik2/scripts/__init__.py
klustakwik2/numerics/__init__.py
klustakwik2/numerics/numbalib/m_step.py
klustakwik2/numerics/numbalib/__init__.py
klustakwik2/numerics/cylib/m_step_cy.pyx
klustakwik2/numerics/cylib/compute_cluster_penalties_cy.pyx
klustakwik2/numerics/cylib/m_step_cy.so
klustakwik2/numerics/cylib/compute_cluster_masks_cy.pyx
klustakwik2/numerics/cylib/e_step_cy.pyx
klustakwik2/numerics/cylib/e_step_cy.so
klustakwik2/numerics/cylib/compute_cluster_masks_cy.so
klustakwik2/numerics/cylib/compute_cluster_penalties_cy.so
klustakwik2/numerics/cylib/compute_cluster_masks.py
klustakwik2/numerics/cylib/compute_cluster_penalties_cy.c
klustakwik2/numerics/cylib/compute_cluster_masks_cy.c
klustakwik2/numerics/cylib/e_step_cy.cpp
klustakwik2/numerics/cylib/m_step_cy.c
klustakwik2/numerics/cylib/masks_cy.pyx
klustakwik2/numerics/cylib/masks_cy.so
klustakwik2/numerics/cylib/m_step.py
klustakwik2/numerics/cylib/compute_cluster_penalties.py
klustakwik2/numerics/cylib/masks_cy.cpp
klustakwik2/numerics/cylib/masks.py
klustakwik2/numerics/cylib/e_step.py
klustakwik2/numerics/cylib/__init__.py
klustakwik2/tests/test_partitioning.py
klustakwik2/tests/test_compute_covariance_matrix.py
klustakwik2/tests/test_io.py
klustakwik2/tests/test_compute_cluster_masks.py
klustakwik2/tests/test_mask_starts.py
klustakwik2/tests/test_synthetic_data.py
klustakwik2/tests/test_linear_algebra.py
klustakwik2/tests/__init__.py
