Metadata-Version: 2.1
Name: klustakwik2
Version: 0.2.7
Summary: Clustering for high dimensional neural data
Home-page: https://github.com/kwikteam/klustakwik2
Author: UNKNOWN
Author-email: UNKNOWN
License: BSD
Keywords: klustakwik2,data analysis,electrophysiology,neuroscience,clustering
Platform: UNKNOWN
Classifier: Development Status :: 4 - Beta
Classifier: Intended Audience :: Developers
Classifier: License :: OSI Approved :: BSD License
Classifier: Natural Language :: English
Classifier: Programming Language :: Python :: 2
Classifier: Programming Language :: Python :: 2.7
Classifier: Programming Language :: Python :: 3
Classifier: Programming Language :: Python :: 3.3
Classifier: Programming Language :: Python :: 3.4
